hmac_http/__init__.py
hmac_http-1.0.2.dist-info/LICENSE
hmac_http-1.0.2.dist-info/METADATA
hmac_http-1.0.2.dist-info/WHEEL
hmac_http-1.0.2.dist-info/top_level.txt
hmac_http-1.0.2.dist-info/RECORD
